pygo_API/__init__.py
pygo_API/api.py
pygo_API/cache.py
pygo_API/common.py
tests/__init__.py
tests/test_card_class.py
tests/test_image_class.py
pygo_API-0.1.2.dist-info/LICENSE
pygo_API-0.1.2.dist-info/METADATA
pygo_API-0.1.2.dist-info/WHEEL
pygo_API-0.1.2.dist-info/top_level.txt
pygo_API-0.1.2.dist-info/RECORD
