Metadata-Version: 2.1
Name: pygo_API
Version: 0.1.2
Summary: A simple tool to utilize the YGOProDeck API as a Python module
Home-page: https://github.com/Yeet195/pygo_API
License: MIT
Classifier: Programming Language :: Python :: 3
Classifier: License :: OSI Approved :: MIT License
Classifier: Operating System :: OS Independent
License-File: LICENSE
Requires-Dist: requests >=2.0
